README.md
setup.py
pioner/__init__.py
pioner/__main__.py
pioner/application.py
pioner/context.py
pioner/errors.py
pioner.egg-info/PKG-INFO
pioner.egg-info/SOURCES.txt
pioner.egg-info/dependency_links.txt
pioner.egg-info/requires.txt
pioner.egg-info/top_level.txt
pioner/functions/__init__.py
pioner/functions/container/__init__.py
pioner/functions/container/homebrew/__init__.py
pioner/functions/container/homebrew/avalanche_coordinator.py
pioner/functions/container/homebrew/avalanche_worker.py
pioner/functions/container/homebrew/bell.py
pioner/functions/container/homebrew/hawk_telegram.py
pioner/functions/container/homebrew/hawk_web.py
pioner/functions/container/homebrew/spirit.py
pioner/functions/container/third_party/__init__.py
pioner/functions/container/third_party/coredhcp.py
pioner/functions/container/third_party/coredns.py
pioner/functions/container/third_party/openntp.py
pioner/functions/container/third_party/tor_socks_proxy.py
pioner/functions/os/__init__.py
pioner/functions/os/system.py
pioner/functions/os/network/__init__.py
pioner/functions/os/network/interface.py
pioner/functions/os/service/__init__.py
pioner/functions/os/service/iptables.py
pioner/functions/os/service/network.py
pioner/functions/os/service/openssh.py
pioner/functions/os/service/system.py
pioner/os/__init__.py
pioner/os/distributive.py
pioner/os/system.py
pioner/os/file_hierarchies/__init__.py
pioner/os/file_hierarchies/alpine_file_hierarchy.py
pioner/os/file_hierarchies/ubuntu_file_hierarchy.py
pioner/os/init_systems/__init__.py
pioner/os/init_systems/initd_init_system.py
pioner/os/init_systems/openrc_init_system.py